printify/__init__.py
printify/main.py
printify-0.0.1.dist-info/LICENSE
printify-0.0.1.dist-info/METADATA
printify-0.0.1.dist-info/WHEEL
printify-0.0.1.dist-info/top_level.txt
printify-0.0.1.dist-info/RECORD
