Metadata-Version: 2.1
Name: printify
Version: 0.0.1
Summary: A small printer package to get some better looking print statements.
Author-email: Amir <grjiamir@gmail.com>
Project-URL: Homepage, https://github.com/amirxpr/python-pretty-print.git
Classifier: Programming Language :: Python :: 3
Classifier: License :: OSI Approved :: MIT License
Classifier: Operating System :: OS Independent
Requires-Python: >=3.7
License-File: LICENSE
